Metadata-Version: 2.1
Name: cloudshell-shell-automation-tests
Version: 0.17.4
Summary: QualiSystems automation tests for Shells
Home-page: http://www.qualisystem.com/
Author-email: info@qualisystems.com
Requires-Python: ~=3.10
Requires-Dist: click (~=8.0)
Requires-Dist: cloudshell-automation-api (~=2021.0)
Requires-Dist: cloudshell-rest-api (~=8.2)
Requires-Dist: cryptography (~=3.1)
Requires-Dist: pysmb (~=1.1)
Requires-Dist: pyvmomi (~=6.7)
Requires-Dist: PyYAML (<7,>=6.0.1)
Requires-Dist: requests (~=2.20)
Requires-Dist: teamcity-messages (~=1.21)
Requires-Dist: xmltodict (~=0.12.0)
Requires-Dist: pydantic (~=1.10)
Requires-Dist: paramiko (~=2.7)
Requires-Dist: tftpy (~=0.8)
Requires-Dist: retrying (~=1.3)
